qnpy/__init__.py
qnpy/calculator.py
qnpy/data.json
qnpy_template-2.0.2.data/data/sample.json
qnpy_template-2.0.2.dist-info/LICENSE.txt
qnpy_template-2.0.2.dist-info/METADATA
qnpy_template-2.0.2.dist-info/WHEEL
qnpy_template-2.0.2.dist-info/entry_points.txt
qnpy_template-2.0.2.dist-info/top_level.txt
qnpy_template-2.0.2.dist-info/zip-safe
qnpy_template-2.0.2.dist-info/RECORD
