Metadata-Version: 2.1
Name: qnpy-template
Version: 2.0.2
Summary: python library template repo
Author-email: World Automation <allworldautomation@gmail.com>
License: Copyright (C) Nan Qin - All Rights Reserved
Keywords: template
Classifier: Programming Language :: Python :: 3
Classifier: Programming Language :: Python :: 3.8
Classifier: Programming Language :: Python :: 3.9
Requires-Python: >=3.7
License-File: LICENSE.txt
Requires-Dist: numpy
Provides-Extra: test
Requires-Dist: pytest ; extra == 'test'
Requires-Dist: pytest-cov ; extra == 'test'
